temporian/BUILD
temporian/__init__.py
temporian/api/BUILD
temporian/api/__init__.py
temporian/api/duration.py
temporian/beam/BUILD
temporian/beam/__init__.py
temporian/beam/evaluation.py
temporian/beam/implementation_lib.py
temporian/beam/io/BUILD
temporian/beam/io/csv.py
temporian/beam/io/dict.py
temporian/beam/io/np_array_coder.py
temporian/beam/io/tensorflow.py
temporian/beam/io/test/BUILD
temporian/beam/io/test/csv_test.py
temporian/beam/io/test/dict_test.py
temporian/beam/io/test/np_array_coder_test.py
temporian/beam/io/test/tensorflow_test.py
temporian/beam/operators/BUILD
temporian/beam/operators/__init__.py
temporian/beam/operators/add_index.py
temporian/beam/operators/base.py
temporian/beam/operators/binary/BUILD
temporian/beam/operators/binary/__init__.py
temporian/beam/operators/binary/binary.py
temporian/beam/operators/cast.py
temporian/beam/operators/drop_index.py
temporian/beam/operators/filter.py
temporian/beam/operators/filter_empty_index.py
temporian/beam/operators/filter_moving_count.py
temporian/beam/operators/glue.py
temporian/beam/operators/lag.py
temporian/beam/operators/leak.py
temporian/beam/operators/prefix.py
temporian/beam/operators/propagate.py
temporian/beam/operators/rename.py
temporian/beam/operators/resample.py
temporian/beam/operators/scalar/BUILD
temporian/beam/operators/scalar/__init__.py
temporian/beam/operators/scalar/scalar.py
temporian/beam/operators/select.py
temporian/beam/operators/test/BUILD
temporian/beam/operators/test/add_index_test.py
temporian/beam/operators/test/binary_test.py
temporian/beam/operators/test/cast_test.py
temporian/beam/operators/test/drop_index_test.py
temporian/beam/operators/test/filter_empty_index_test.py
temporian/beam/operators/test/filter_moving_count_test.py
temporian/beam/operators/test/filter_test.py
temporian/beam/operators/test/glue_test.py
temporian/beam/operators/test/lag_test.py
temporian/beam/operators/test/leak_test.py
temporian/beam/operators/test/prefix_test.py
temporian-0.9.0.dist-info/LICENSE
temporian-0.9.0.dist-info/METADATA
temporian-0.9.0.dist-info/WHEEL
temporian-0.9.0.dist-info/RECORD
