Metadata-Version: 2.1
Name: temporian
Version: 0.9.0
Summary: Temporian is a Python package for feature engineering of temporal data, focusing on preventing common modeling errors and providing a simple and powerful API, a first-class iterative development experience, and efficient and well-tested implementations of common and not-so-common temporal data preprocessing functions.
Home-page: https://github.com/google/temporian
License: Apache 2.0
Author: Mathieu Guillame-Bert, Braulio Ríos, Guillermo Etchebarne, Ian Spektor, Richard Stotz
Author-email: gbm@google.com
Maintainer: Mathieu Guillame-Bert
Maintainer-email: gbm@google.com
Requires-Python: >=3.8,<3.12
Classifier: Development Status :: 2 - Pre-Alpha
Classifier: Intended Audience :: Developers
Classifier: Intended Audience :: Education
Classifier: Intended Audience :: Science/Research
Classifier: License :: OSI Approved :: Apache Software License
Classifier: License :: Other/Proprietary License
Classifier: Programming Language :: Python :: 3
Classifier: Programming Language :: Python :: 3.8
Classifier: Programming Language :: Python :: 3.9
Classifier: Programming Language :: Python :: 3.10
Classifier: Programming Language :: Python :: 3.11
Classifier: Topic :: Scientific/Engineering
Classifier: Topic :: Scientific/Engineering :: Artificial Intelligence
Classifier: Topic :: Scientific/Engineering :: Mathematics
Classifier: Topic :: Software Development
Classifier: Topic :: Software Development :: Libraries
Classifier: Topic :: Software Development :: Libraries :: Python Modules
Provides-Extra: all
Provides-Extra: beam
Provides-Extra: polars
Provides-Extra: tensorflow
Requires-Dist: absl-py (>=1.3.0,<2.0.0)
Requires-Dist: apache-beam (>=2.48.0,<3.0.0) ; extra == "beam" or extra == "all"
Requires-Dist: matplotlib (>=3.7.1,<4.0.0)
Requires-Dist: pandas (>=1.5.2)
Requires-Dist: polars (>=0.20.15,<0.21.0) ; extra == "polars" or extra == "all"
Requires-Dist: protobuf (>=3.20.3)
Requires-Dist: tensorflow (>=2.12.0,<2.16) ; extra == "tensorflow" or extra == "all"
Project-URL: Repository, https://github.com/google/temporian
